{"rows":[{"cal_year":"2018.0","total":3445170.32,"gp_nm":"Miscellaneous"}, 
 {"cal_year":"2010.0","total":46221.13,"gp_nm":"Purchasing / MBE/WBE"}, 
 {"cal_year":"2019.0","total":340007.30,"gp_nm":"Special Operations"}, 
 {"cal_year":"2009.0","total":350495.71,"gp_nm":"Organized Crime"}, 
 {"cal_year":"2008.0","total":23265.89,"gp_nm":"Recruiting"}, 
 {"cal_year":"2018.0","total":200019.34,"gp_nm":"Organized Crime"}, 
 {"cal_year":"2010.0","total":75467.77,"gp_nm":"Vehicle / Equipment Maintenance"}, 
 {"cal_year":"2016.0","total":651299.21,"gp_nm":"Miscellaneous"}, 
 {"cal_year":"2018.0","total":25854.53,"gp_nm":"Internal Affairs"}, 
 {"cal_year":"2018.0","total":77978.78,"gp_nm":"Mounted Patrol Facilities"}, 
 {"cal_year":"2017.0","total":520499.93,"gp_nm":"Air Operations"}, 
 {"cal_year":"2020.0","total":73596.3,"gp_nm":"Organized Crime"}, 
 {"cal_year":"2008.0","total":1224.69,"gp_nm":"Accreditation/Inspections"}, 
 {"cal_year":"2017.0","total":14367.0,"gp_nm":"Park Patrol/Rangers JUF"}, 
 {"cal_year":"2008.0","total":8542.02,"gp_nm":"Internal Affairs"}, 
 {"cal_year":"2009.0","total":25656.57,"gp_nm":"Personnel / Training"}, 
 {"cal_year":"2014.0","total":295955.15,"gp_nm":"Organized Crime"}, 
 {"cal_year":"2013.0","total":523570.34,"gp_nm":"Forensics Science Services"}, 
 {"cal_year":"2010.0","total":407033.78,"gp_nm":"Patrol"}, 
 {"cal_year":"2011.0","total":793850.08,"gp_nm":"Centralized Investigations"}, 
 {"cal_year":"2017.0","total":830398.58,"gp_nm":"Training"}, 
 {"cal_year":"2010.0","total":115822.95,"gp_nm":"Personnel / Training"}, 
 {"cal_year":"2010.0","total":171806.14,"gp_nm":"Organized Crime"}, 
 {"cal_year":"2015.0","total":1033048.85,"gp_nm":"Patrol"}, 
 {"cal_year":"2019.0","total":142928.43,"gp_nm":"Recruiting"}, 
 {"cal_year":"2009.0","total":60291.15,"gp_nm":"Other Requirements"}, 
 {"cal_year":"2019.0","total":332287.53,"gp_nm":"Community Partnerships"}, 
 {"cal_year":"2017.0","total":570526.95,"gp_nm":"Miscellaneous"}, 
 {"cal_year":"2009.0","total":114662.85,"gp_nm":"Special Operations"}, 
 {"cal_year":"2016.0","total":500183.55,"gp_nm":"Air Operations"}, 
 {"cal_year":"2013.0","total":177801.23,"gp_nm":"Specialized Patrol & Events Planning"}, 
 {"cal_year":"2013.0","total":125788.42,"gp_nm":"Patrol Support"}, 
 {"cal_year":"2016.0","total":898101.02,"gp_nm":"Training"}, 
 {"cal_year":"2013.0","total":471268.09,"gp_nm":"Air Operations"}, 
 {"cal_year":"2020.0","total":2890254.29,"gp_nm":"Strategic Support"}, 
 {"cal_year":"2008.0","total":84106.12,"gp_nm":"Organized Crime"}, 
 {"cal_year":"2013.0","total":1702288.42,"gp_nm":"Patrol"}, 
 {"cal_year":"2013.0","total":622357.55,"gp_nm":"Training"}, 
 {"cal_year":"2008.0","total":2798.73,"gp_nm":"Financial Monitoring / Budgeting"}, 
 {"cal_year":"2012.0","total":408487.65,"gp_nm":"Victim Services"}, 
 {"cal_year":"2010.0","total":50887.10,"gp_nm":"Park Police"}, 
 {"cal_year":"2008.0","total":330.12,"gp_nm":"Victim Services"}, 
 {"cal_year":"2010.0","total":514560.09,"gp_nm":"Forensics Science Services"}, 
 {"cal_year":"2013.0","total":6775693.47,"gp_nm":"Miscellaneous"}, 
 {"cal_year":"2018.0","total":2740220.52,"gp_nm":"Forensics Science Services"}, 
 {"cal_year":"2009.0","total":355863.68,"gp_nm":"Patrol"}, 
 {"cal_year":"2018.0","total":310576.94,"gp_nm":"Park Patrol/Rangers JUF"}, 
 {"cal_year":"2009.0","total":477063.35,"gp_nm":"Victim Services"}, 
 {"cal_year":"2015.0","total":161176.49,"gp_nm":"Specialized Patrol & Events Planning"}, 
 {"cal_year":"2019.0","total":18458.16,"gp_nm":"Internal Affairs"}, 
 {"cal_year":"2009.0","total":85100.37,"gp_nm":"Traffic Enforcement"}, 
 {"cal_year":"2015.0","total":536081.33,"gp_nm":"Air Operations"}, 
 {"cal_year":"2012.0","total":27757.89,"gp_nm":"Recruiting"}, 
 {"cal_year":"2015.0","total":1920552.68,"gp_nm":"Departmental Support Services"}, 
 {"cal_year":"2013.0","total":50335.33,"gp_nm":"Recruiting"}, 
 {"cal_year":"2014.0","total":339749.67,"gp_nm":"Patrol Support"}, 
 {"cal_year":"2020.0","total":24697.12,"gp_nm":"Traffic Enforcement"}, 
 {"cal_year":"2008.0","total":89393.65,"gp_nm":"Information Technology Support"}, 
 {"cal_year":"2013.0","total":74474.11,"gp_nm":"Internal Affairs"}, 
 {"cal_year":"2010.0","total":14520.62,"gp_nm":"Airport Police"}, 
 {"cal_year":"2009.0","total":49342.44,"gp_nm":"Risk Prevention"}, 
 {"cal_year":"2014.0","total":180629.99,"gp_nm":"Specialized Patrol & Events Planning"}, 
 {"cal_year":"2010.0","total":50501.62,"gp_nm":"Internal Affairs"}, 
 {"cal_year":"2010.0","total":355749.68,"gp_nm":"Facility Expenses"}, 
 {"cal_year":"2018.0","total":1602138.29,"gp_nm":"Departmental Support Services"}, 
 {"cal_year":"2020.0","total":238656.33,"gp_nm":"Air Operations"}, 
 {"cal_year":"2013.0","total":218761.55,"gp_nm":"Traffic Enforcement"}, 
 {"cal_year":"2017.0","total":242641.03,"gp_nm":"Community Partnerships"}, 
 {"cal_year":"2015.0","total":927756.64,"gp_nm":"Centralized Investigations"}, 
 {"cal_year":"2017.0","total":1155968.08,"gp_nm":"Centralized Investigations"}, 
 {"cal_year":"2014.0","total":47880.02,"gp_nm":"Recruiting"}, 
 {"cal_year":"2010.0","total":481800.40,"gp_nm":"Victim Services"}, 
 {"cal_year":"2012.0","total":118234.82,"gp_nm":"Other Requirements"}, 
 {"cal_year":"2016.0","total":121617.07,"gp_nm":"Transfers"}, 
 {"cal_year":"2008.0","total":47443.99,"gp_nm":"Traffic Enforcement"}, 
 {"cal_year":"2011.0","total":108309.62,"gp_nm":"Patrol Support"}, 
 {"cal_year":"2016.0","total":84639.61,"gp_nm":"Communications"}, 
 {"cal_year":"2018.0","total":453201.92,"gp_nm":"Patrol Support"}, 
 {"cal_year":"2008.0","total":2693552.19,"gp_nm":"Miscellaneous"}, 
 {"cal_year":"2009.0","total":34817.99,"gp_nm":"Vehicle / Equipment Maintenance"}, 
 {"cal_year":"2011.0","total":101461.40,"gp_nm":"Internal Affairs"}, 
 {"cal_year":"2008.0","total":192122.66,"gp_nm":"Forensics Science Services"}, 
 {"cal_year":"2011.0","total":30349.31,"gp_nm":"Park Police"}, 
 {"cal_year":"2019.0","total":1025651.20,"gp_nm":"Centralized Investigations"}, 
 {"cal_year":"2011.0","total":28012.95,"gp_nm":"Specialized Patrol & Events Planning"}, 
 {"cal_year":"2010.0","total":111314.40,"gp_nm":"Communications and Emergency Planning"}, 
 {"cal_year":"2011.0","total":306822.10,"gp_nm":"Traffic Enforcement"}, 
 {"cal_year":"2018.0","total":6748273.14,"gp_nm":"Strategic Support"}, 
 {"cal_year":"2016.0","total":90702.81,"gp_nm":"Victim Services"}, 
 {"cal_year":"2015.0","total":231400.38,"gp_nm":"Organized Crime"}, 
 {"cal_year":"2009.0","total":21586.76,"gp_nm":"East Side Story"}, 
 {"cal_year":"2010.0","total":40325.06,"gp_nm":"Recruiting"}, 
 {"cal_year":"2013.0","total":1278060.54,"gp_nm":"Community Partnerships"}, 
 {"cal_year":"2016.0","total":5350436.97,"gp_nm":"Strategic Support"}, 
 {"cal_year":"2008.0","total":19400.27,"gp_nm":"Purchasing / MBE/WBE"}, 
 {"cal_year":"2012.0","total":6153903.35,"gp_nm":"Strategic Support"}, 
 {"cal_year":"2014.0","total":4975448.92,"gp_nm":"Strategic Support"}, 
 {"cal_year":"2008.0","total":25715.02,"gp_nm":"Special Operations"}, 
 {"cal_year":"2016.0","total":666435.75,"gp_nm":"Community Partnerships"}, 
 {"cal_year":"2020.0","total":509171.38,"gp_nm":"Centralized Investigations"}, 
 {"cal_year":"2016.0","total":99644.89,"gp_nm":"Other Requirements"}, 
 {"cal_year":"2015.0","total":195742.71,"gp_nm":"Mounted Patrol Facilities"}, 
 {"cal_year":"2017.0","total":1528669.82,"gp_nm":"Forensics Science Services"}, 
 {"cal_year":"2019.0","total":438201.10,"gp_nm":"Patrol Support"}, 
 {"cal_year":"2016.0","total":36190.47,"gp_nm":"Forensic Laboratory Renovation"}, 
 {"cal_year":"2008.0","total":275733.55,"gp_nm":"Centralized Investigations"}, 
 {"cal_year":"2017.0","total":1899795.43,"gp_nm":"Departmental Support Services"}, 
 {"cal_year":"2010.0","total":162687.62,"gp_nm":"Administration & Management"}, 
 {"cal_year":"2015.0","total":73423.71,"gp_nm":"MLK Evidence Warehouse Expansion"}, 
 {"cal_year":"2010.0","total":38132.72,"gp_nm":"Risk Management"}, 
 {"cal_year":"2016.0","total":207946.91,"gp_nm":"Organized Crime"}, 
 {"cal_year":"2011.0","total":747258.71,"gp_nm":"Community Partnerships"}, 
 {"cal_year":"2008.0","total":7394.43,"gp_nm":"Vehicle / Equipment Maintenance"}, 
 {"cal_year":"2010.0","total":5100065.44,"gp_nm":"Miscellaneous"}, 
 {"cal_year":"2009.0","total":556925.04,"gp_nm":"Forensics Science Services"}, 
 {"cal_year":"2010.0","total":151725.80,"gp_nm":"Special Operations"}, 
 {"cal_year":"2016.0","total":133954.17,"gp_nm":"Special Operations"}, 
 {"cal_year":"2014.0","total":565970.29,"gp_nm":"Community Partnerships"}, 
 {"cal_year":"2009.0","total":45333.79,"gp_nm":"Internal Affairs"}, 
 {"cal_year":"2019.0","total":813577.35,"gp_nm":"Training"}, 
 {"cal_year":"2008.0","total":94496.41,"gp_nm":"Other Requirements"}, 
 {"cal_year":"2011.0","total":26531.40,"gp_nm":"Recruiting"}, 
 {"cal_year":"2015.0","total":712187.87,"gp_nm":"Training"}, 
 {"cal_year":"2020.0","total":42318.48,"gp_nm":"Specialized Patrol & Events Planning"}, 
 {"cal_year":"2017.0","total":1170.0,"gp_nm":"Forensic Laboratory Renovation"}, 
 {"cal_year":"2012.0","total":95748.95,"gp_nm":"Communications"}, 
 {"cal_year":"2015.0","total":356009.22,"gp_nm":"Patrol Support"}, 
 {"cal_year":"2013.0","total":1915663.66,"gp_nm":"Departmental Support Services"}, 
 {"cal_year":"2014.0","total":250242.97,"gp_nm":"Traffic Enforcement"}, 
 {"cal_year":"2014.0","total":2514334.06,"gp_nm":"Miscellaneous"}, 
 {"cal_year":"2017.0","total":2220981.59,"gp_nm":"Patrol"}, 
 {"cal_year":"2011.0","total":1270659.12,"gp_nm":"Patrol"}, 
 {"cal_year":"2008.0","total":150679.87,"gp_nm":"Personnel / Training"}, 
 {"cal_year":"2010.0","total":255010.98,"gp_nm":"Information Technology Support"}, 
 {"cal_year":"2012.0","total":162983.44,"gp_nm":"Specialized Patrol & Events Planning"}, 
 {"cal_year":"2011.0","total":165417.26,"gp_nm":"Other Requirements"}, 
 {"cal_year":"2018.0","total":1281737.48,"gp_nm":"Centralized Investigations"}, 
 {"cal_year":"2008.0","total":56495.01,"gp_nm":"Community Partnerships"}, 
 {"cal_year":"2011.0","total":1718245.83,"gp_nm":"Departmental Support Services"}, 
 {"cal_year":"2014.0","total":103096.5,"gp_nm":"Mounted Patrol Facilities"}, 
 {"cal_year":"2009.0","total":96947.73,"gp_nm":"Communications (9-1-1/ Dispatch Operations)"}, 
 {"cal_year":"2017.0","total":322660.49,"gp_nm":"Organized Crime"}, 
 {"cal_year":"2008.0","total":55193.64,"gp_nm":"Administration & Management"}, 
 {"cal_year":"2010.0","total":123421.26,"gp_nm":"Patrol Support"}, 
 {"cal_year":"2015.0","total":808253.13,"gp_nm":"Forensics Science Services"}, 
 {"cal_year":"2009.0","total":210908.70,"gp_nm":"Community Partnerships"}, 
 {"cal_year":"2017.0","total":137284.11,"gp_nm":"Recruiting"}, 
 {"cal_year":"2015.0","total":49297.11,"gp_nm":"Recruiting"}, 
 {"cal_year":"2019.0","total":162662.33,"gp_nm":"Specialized Patrol & Events Planning"}, 
 {"cal_year":"2008.0","total":16592.97,"gp_nm":"Patrol Support"}, 
 {"cal_year":"2017.0","total":179543.25,"gp_nm":"Patrol Support"}, 
 {"cal_year":"2011.0","total":386831.20,"gp_nm":"Air Operations"}, 
 {"cal_year":"2019.0","total":51878.90,"gp_nm":"Traffic Enforcement"}, 
 {"cal_year":"2015.0","total":35709.30,"gp_nm":"Traffic Enforcement"}, 
 {"cal_year":"2012.0","total":33682.25,"gp_nm":"Patrol Support"}, 
 {"cal_year":"2010.0","total":489957.52,"gp_nm":"Training"}, 
 {"cal_year":"2010.0","total":8004.41,"gp_nm":"Financial Monitoring / Budgeting"}, 
 {"cal_year":"2020.0","total":37787.16,"gp_nm":"Communications"}, 
 {"cal_year":"2012.0","total":1772763.42,"gp_nm":"Departmental Support Services"}, 
 {"cal_year":"2020.0","total":3993041.34,"gp_nm":"Patrol"}, 
 {"cal_year":"2013.0","total":5848630.51,"gp_nm":"Strategic Support"}, 
 {"cal_year":"2009.0","total":3250.0,"gp_nm":"Public Information"}, 
 {"cal_year":"2012.0","total":6248314.59,"gp_nm":"Miscellaneous"}, 
 {"cal_year":"2011.0","total":22369.36,"gp_nm":"Communications"}, 
 {"cal_year":"2014.0","total":455065.08,"gp_nm":"Air Operations"}, 
 {"cal_year":"2008.0","total":6518.10,"gp_nm":"East Side Story"}, 
 {"cal_year":"2008.0","total":71901.85,"gp_nm":"Air Support"}, 
 {"cal_year":"2015.0","total":131033.03,"gp_nm":"Special Operations"}, 
 {"cal_year":"2015.0","total":52893.77,"gp_nm":"Park Patrol/Rangers JUF"}, 
 {"cal_year":"2013.0","total":64619.75,"gp_nm":"Victim Services"}, 
 {"cal_year":"2017.0","total":113634.38,"gp_nm":"Mounted Patrol Facilities"}, 
 {"cal_year":"2009.0","total":651303.17,"gp_nm":"Centralized Investigations"}, 
 {"cal_year":"2019.0","total":1358261.79,"gp_nm":"Miscellaneous"}, 
 {"cal_year":"2009.0","total":3585415.75,"gp_nm":"Miscellaneous"}, 
 {"cal_year":"2009.0","total":19749.06,"gp_nm":"Communications and Emergency Planning"}, 
 {"cal_year":"2013.0","total":141233.32,"gp_nm":"Organized Crime"}, 
 {"cal_year":"2014.0","total":24790.02,"gp_nm":"Other Requirements"}, 
 {"cal_year":"2016.0","total":98352.56,"gp_nm":"Park Patrol/Rangers JUF"}, 
 {"cal_year":"2019.0","total":1776410.24,"gp_nm":"Departmental Support Services"}, 
 {"cal_year":"2014.0","total":997405.47,"gp_nm":"Training"}, 
 {"cal_year":"2016.0","total":1702715.46,"gp_nm":"Patrol"}, 
 {"cal_year":"2016.0","total":275410.47,"gp_nm":"Patrol Support"}, 
 {"cal_year":"2015.0","total":8241208.07,"gp_nm":"Strategic Support"}, 
 {"cal_year":"2019.0","total":78138.65,"gp_nm":"Communications"}, 
 {"cal_year":"2017.0","total":200238.75,"gp_nm":"Specialized Patrol & Events Planning"}, 
 {"cal_year":"2019.0","total":184119.61,"gp_nm":"Mounted Patrol Facilities"}, 
 {"cal_year":"2014.0","total":57424.05,"gp_nm":"Communications"}, 
 {"cal_year":"2010.0","total":68036.0,"gp_nm":"Other Requirements"}, 
 {"cal_year":"2020.0","total":206906.42,"gp_nm":"Special Operations"}, 
 {"cal_year":"2011.0","total":5769731.24,"gp_nm":"Strategic Command"}, 
 {"cal_year":"2014.0","total":936786.05,"gp_nm":"Centralized Investigations"}, 
 {"cal_year":"2008.0","total":1270012.07,"gp_nm":"Strategic Command"}, 
 {"cal_year":"2018.0","total":88279.10,"gp_nm":"Traffic Enforcement"}, 
 {"cal_year":"2017.0","total":99604.56,"gp_nm":"Communications"}, 
 {"cal_year":"2009.0","total":221467.40,"gp_nm":"Administration & Management"}, 
 {"cal_year":"2009.0","total":69854.36,"gp_nm":"Purchasing / MBE/WBE"}, 
 {"cal_year":"2020.0","total":1096467.42,"gp_nm":"Forensics Science Services"}, 
 {"cal_year":"2013.0","total":102797.84,"gp_nm":"Communications"}, 
 {"cal_year":"2012.0","total":1062989.72,"gp_nm":"Patrol"}, 
 {"cal_year":"2009.0","total":70655.38,"gp_nm":"Patrol Support"}, 
 {"cal_year":"2019.0","total":8287428.22,"gp_nm":"Strategic Support"}, 
 {"cal_year":"2017.0","total":30353.21,"gp_nm":"Victim Services"}, 
 {"cal_year":"2010.0","total":3375.0,"gp_nm":"Public Information"}, 
 {"cal_year":"2020.0","total":380292.20,"gp_nm":"Training"}, 
 {"cal_year":"2015.0","total":1714407.36,"gp_nm":"Miscellaneous"}, 
 {"cal_year":"2018.0","total":825731.38,"gp_nm":"Training"}, 
 {"cal_year":"2012.0","total":742547.26,"gp_nm":"Centralized Investigations"}, 
 {"cal_year":"2020.0","total":58952.47,"gp_nm":"Recruiting"}, 
 {"cal_year":"2010.0","total":383167.55,"gp_nm":"Departmental Support Services"}, 
 {"cal_year":"2018.0","total":414109.53,"gp_nm":"Air Operations"}, 
 {"cal_year":"2015.0","total":460398.14,"gp_nm":"Other Requirements"}, 
 {"cal_year":"2017.0","total":1655.0,"gp_nm":"MLK Evidence Warehouse Expansion"}, 
 {"cal_year":"2008.0","total":1045.53,"gp_nm":"Public Information"}, 
 {"cal_year":"2019.0","total":2629618.70,"gp_nm":"Forensics Science Services"}, 
 {"cal_year":"2020.0","total":184406.06,"gp_nm":"Community Partnerships"}, 
 {"cal_year":"2015.0","total":480807.25,"gp_nm":"Community Partnerships"}, 
 {"cal_year":"2009.0","total":14522.77,"gp_nm":"Airport Police"}, 
 {"cal_year":"2016.0","total":680296.45,"gp_nm":"Forensics Science Services"}, 
 {"cal_year":"2010.0","total":749968.72,"gp_nm":"Centralized Investigations"}, 
 {"cal_year":"2018.0","total":2887310.52,"gp_nm":"Patrol"}, 
 {"cal_year":"2016.0","total":920832.17,"gp_nm":"Centralized Investigations"}, 
 {"cal_year":"2012.0","total":954606.66,"gp_nm":"Community Partnerships"}, 
 {"cal_year":"2008.0","total":82006.56,"gp_nm":"Training"}, 
 {"cal_year":"2012.0","total":261540.06,"gp_nm":"Air Operations"}, 
 {"cal_year":"2011.0","total":7954968.87,"gp_nm":"Miscellaneous"}, 
 {"cal_year":"2017.0","total":6475037.78,"gp_nm":"Strategic Support"}, 
 {"cal_year":"2019.0","total":96262.66,"gp_nm":"Victim Services"}, 
 {"cal_year":"2010.0","total":985110.04,"gp_nm":"Community Partnerships"}, 
 {"cal_year":"2013.0","total":986769.08,"gp_nm":"Centralized Investigations"}, 
 {"cal_year":"2018.0","total":59672.61,"gp_nm":"Victim Services"}, 
 {"cal_year":"2020.0","total":580367.08,"gp_nm":"Departmental Support Services"}, 
 {"cal_year":"2012.0","total":113329.42,"gp_nm":"Special Operations"}, 
 {"cal_year":"2016.0","total":2264173.30,"gp_nm":"Departmental Support Services"}, 
 {"cal_year":"2014.0","total":123144.52,"gp_nm":"Special Operations"}, 
 {"cal_year":"2009.0","total":9404.73,"gp_nm":"Financial Monitoring / Budgeting"}, 
 {"cal_year":"2017.0","total":57508.64,"gp_nm":"Traffic Enforcement"}, 
 {"cal_year":"2014.0","total":2083.34,"gp_nm":"Victim Services"}, 
 {"cal_year":"2016.0","total":91432.52,"gp_nm":"Recruiting"}, 
 {"cal_year":"2018.0","total":4032609.22,"gp_nm":"Land Acquisition Northwest Substation"}, 
 {"cal_year":"2020.0","total":5216.11,"gp_nm":"Victim Services"}, 
 {"cal_year":"2018.0","total":546126.51,"gp_nm":"Community Partnerships"}, 
 {"cal_year":"2018.0","total":138316.93,"gp_nm":"Recruiting"}, 
 {"cal_year":"2015.0","total":65440.99,"gp_nm":"Victim Services"}, 
 {"cal_year":"2009.0","total":57481.29,"gp_nm":"Recruiting"}, 
 {"cal_year":"2016.0","total":269202.48,"gp_nm":"Specialized Patrol & Events Planning"}, 
 {"cal_year":"2020.0","total":908806.15,"gp_nm":"Miscellaneous"}, 
 {"cal_year":"2018.0","total":551656.88,"gp_nm":"Transfers"}, 
 {"cal_year":"2017.0","total":198171.29,"gp_nm":"Special Operations"}, 
 {"cal_year":"2009.0","total":36806.58,"gp_nm":"Air Operations"}, 
 {"cal_year":"2009.0","total":10995.76,"gp_nm":"Risk Management"}, 
 {"cal_year":"2012.0","total":649645.71,"gp_nm":"Forensics Science Services"}, 
 {"cal_year":"2015.0","total":16364.37,"gp_nm":"Internal Affairs"}, 
 {"cal_year":"2020.0","total":49275.62,"gp_nm":"Mounted Patrol Facilities"}, 
 {"cal_year":"2019.0","total":3248806.26,"gp_nm":"Patrol"}, 
 {"cal_year":"2011.0","total":367900.57,"gp_nm":"Training"}, 
 {"cal_year":"2015.0","total":77448.58,"gp_nm":"Communications"}, 
 {"cal_year":"2011.0","total":79521.63,"gp_nm":"Communications and Emergency Planning"}, 
 {"cal_year":"2008.0","total":77671.79,"gp_nm":"Communications (9-1-1/ Dispatch Operations)"}, 
 {"cal_year":"2016.0","total":35334.06,"gp_nm":"Mounted Patrol Facilities"}, 
 {"cal_year":"2011.0","total":1597756.18,"gp_nm":"Strategic Support"}, 
 {"cal_year":"2010.0","total":8697.19,"gp_nm":"East Side Story"}, 
 {"cal_year":"2016.0","total":68924.77,"gp_nm":"Internal Affairs"}, 
 {"cal_year":"2014.0","total":2064839.57,"gp_nm":"Departmental Support Services"}, 
 {"cal_year":"2016.0","total":123437.99,"gp_nm":"Traffic Enforcement"}, 
 {"cal_year":"2011.0","total":254942.39,"gp_nm":"Organized Crime"}, 
 {"cal_year":"2011.0","total":131813.49,"gp_nm":"Special Operations"}, 
 {"cal_year":"2010.0","total":255859.24,"gp_nm":"Traffic Enforcement"}, 
 {"cal_year":"2009.0","total":267237.99,"gp_nm":"Training"}, 
 {"cal_year":"2014.0","total":1826918.95,"gp_nm":"Patrol"}, 
 {"cal_year":"2012.0","total":594007.53,"gp_nm":"Training"}, 
 {"cal_year":"2012.0","total":62800.16,"gp_nm":"Internal Affairs"}, 
 {"cal_year":"2014.0","total":37534.58,"gp_nm":"Park Patrol/Rangers JUF"}, 
 {"cal_year":"2010.0","total":382946.85,"gp_nm":"Air Operations"}, 
 {"cal_year":"2012.0","total":112847.74,"gp_nm":"Organized Crime"}, 
 {"cal_year":"2009.0","total":557.73,"gp_nm":"Accreditation/Inspections"}, 
 {"cal_year":"2012.0","total":177019.80,"gp_nm":"Traffic Enforcement"}, 
 {"cal_year":"2009.0","total":355646.65,"gp_nm":"Information Technology Support"}, 
 {"cal_year":"2008.0","total":121767.07,"gp_nm":"Patrol"}, 
 {"cal_year":"2011.0","total":7954.43,"gp_nm":"Airport Police"}, 
 {"cal_year":"2017.0","total":122664.99,"gp_nm":"Internal Affairs"}, 
 {"cal_year":"2013.0","total":61643.88,"gp_nm":"Special Operations"}, 
 {"cal_year":"2013.0","total":28351.09,"gp_nm":"Other Requirements"}, 
 {"cal_year":"2014.0","total":609286.04,"gp_nm":"Forensics Science Services"}, 
 {"cal_year":"2008.0","total":13359.35,"gp_nm":"Risk Prevention"}, 
 {"cal_year":"2016.0","total":167766.84,"gp_nm":"MLK Evidence Warehouse Expansion"}, 
 {"cal_year":"2018.0","total":126213.49,"gp_nm":"Communications"}, 
 {"cal_year":"2017.0","total":102408.56,"gp_nm":"Transfers"}, 
 {"cal_year":"2014.0","total":22803.69,"gp_nm":"Internal Affairs"}, 
 {"cal_year":"2009.0","total":4209995.95,"gp_nm":"Strategic Command"}, 
 {"cal_year":"2019.0","total":562767.52,"gp_nm":"Air Operations"}, 
 {"cal_year":"2010.0","total":5539128.59,"gp_nm":"Strategic Command"}, 
 {"cal_year":"2008.0","total":123364.41,"gp_nm":"Facility Expenses"}, 
 {"cal_year":"2011.0","total":637943.14,"gp_nm":"Victim Services"}, 
 {"cal_year":"2018.0","total":144697.27,"gp_nm":"Specialized Patrol & Events Planning"}, 
 {"cal_year":"2010.0","total":10500.0,"gp_nm":"NE Sub AIPP"}, 
 {"cal_year":"2018.0","total":294277.31,"gp_nm":"Special Operations"}, 
 {"cal_year":"2009.0","total":303712.86,"gp_nm":"Air Support"}, 
 {"cal_year":"2020.0","total":79392.88,"gp_nm":"Patrol Support"}, 
 {"cal_year":"2011.0","total":732777.34,"gp_nm":"Forensics Science Services"}, 
 {"cal_year":"2009.0","total":437715.05,"gp_nm":"Facility Expenses"}, 
 {"cal_year":"2019.0","total":339643.74,"gp_nm":"Organized Crime"}, 
 {"cal_year":"2009.0","total":35163.74,"gp_nm":"Park Police"}]}